{"chunk_definitions":[{"row":12,"row_count":1,"visible":true,"expansion_state":0,"options":{"engine":"r","label":"unnamed-chunk-4","dev":"png"},"document_id":"3846F972","chunk_id":"c8ed251vfixi5","chunk_label":"unnamed-chunk-1"},{"row":29,"row_count":1,"visible":true,"expansion_state":0,"options":{"engine":"r","label":"import Heritage","dev":"png"},"document_id":"3846F972","chunk_id":"cwssh81xw3x91","chunk_label":"import Heritage"},{"row":44,"row_count":1,"visible":true,"expansion_state":0,"options":{"engine":"r","label":"import fraser Aggregate","dev":"png"},"document_id":"3846F972","chunk_id":"c87r7bjfb232c","chunk_label":"import fraser Aggregate"},{"row":70,"row_count":1,"visible":true,"expansion_state":0,"options":{"engine":"r","label":"merge data","dev":"png"},"document_id":"3846F972","chunk_id":"cqcvgnxlczwfx","chunk_label":"merge data"},{"row":78,"row_count":1,"visible":true,"expansion_state":0,"options":{"engine":"r","label":"components","dev":"png"},"document_id":"3846F972","chunk_id":"c1trlf5flr4e1","chunk_label":"components"}],"doc_write_time":1742349381,"working_dir":null,"default_chunk_options":{"echo":true}}